regridcart/__init__.py
regridcart/coords.py
regridcart/cropping.py
regridcart/domain.py
regridcart/crs/__init__.py
regridcart/crs/cbook.py
regridcart/crs/mapping.py
regridcart/interpolation/__init__.py
regridcart/interpolation/common.py
regridcart/interpolation/backends/__init__.py
regridcart/interpolation/backends/common.py
regridcart/interpolation/backends/pyresample.py
regridcart/interpolation/backends/xesmf.py
tests/__init__.py
tests/test_cflatlon.py
tests/test_regridcart.py
regridcart-0.1.1.dist-info/METADATA
regridcart-0.1.1.dist-info/WHEEL
regridcart-0.1.1.dist-info/top_level.txt
regridcart-0.1.1.dist-info/RECORD
