Metadata-Version: 2.1
Name: regridcart
Version: 0.1.1
Summary: lat/lon and local-cartesian regridding
Home-page: https://github.com/leifdenby/regridcart
Author: Leif Denby
Author-email: leif@denby.eu
License: UNKNOWN
Platform: UNKNOWN
Requires-Dist: xarray
Requires-Dist: netcdf4
Requires-Dist: cartopy
Requires-Dist: xesmf (>=0.4.0)
Provides-Extra: dev
Requires-Dist: pytest ; extra == 'dev'
Requires-Dist: worldview-dl ; extra == 'dev'
Requires-Dist: rioxarray ; extra == 'dev'
Requires-Dist: nbval ; extra == 'dev'
Requires-Dist: nb-black ; extra == 'dev'
Requires-Dist: flake8 ; extra == 'dev'
Requires-Dist: black (==21.9b0) ; extra == 'dev'
Requires-Dist: ipython ; extra == 'dev'
Provides-Extra: lint
Requires-Dist: flake8 ; extra == 'lint'
Requires-Dist: black (==21.9b0) ; extra == 'lint'
Provides-Extra: test
Requires-Dist: pytest ; extra == 'test'
Requires-Dist: worldview-dl ; extra == 'test'
Requires-Dist: rioxarray ; extra == 'test'
Requires-Dist: nbval ; extra == 'test'
Requires-Dist: nb-black ; extra == 'test'
